hafdh_nadhar-0.1.22.dist-info/METADATA
hafdh_nadhar-0.1.22.dist-info/WHEEL
hafdh_nadhar-0.1.22.dist-info/entry_points.txt
hafdh_nadhar/__init__.py
hafdh_nadhar/blur_person.py
hafdh_nadhar/cli.py
hafdh_nadhar/gender_detection.py
hafdh_nadhar/hafdh.py
hafdh_nadhar/helpers.py
hafdh_nadhar/models/.DS_Store
hafdh_nadhar/models/gender_prediction/deploy_gender.prototxt
hafdh_nadhar/models/gender_prediction/gender_net.caffemodel
hafdh_nadhar/models/person_prediction/yolov3-tiny.cfg
hafdh_nadhar/models/person_prediction/yolov3-tiny.weights
hafdh_nadhar/person_detection.py
hafdh_nadhar-0.1.22.dist-info/RECORD
