Metadata-Version: 2.1
Name: hafdh-nadhar
Version: 0.1.22
Summary: Blur humans from a picture
Author-Email: karim-bouchez <bouchez.karim@gmail.com>
License: MIT
Requires-Python: >=3.9
Requires-Dist: opencv-python>=4.8.0.76
Requires-Dist: typer[all]>=0.9.0
